spruceup/__init__.py
spruceup/__main__.py
spruceup/aln_parsing.py
spruceup/aln_writing.py
spruceup/spruceup.py
spruceup-2024.8.20.post1.dist-info/LICENSE
spruceup-2024.8.20.post1.dist-info/METADATA
spruceup-2024.8.20.post1.dist-info/WHEEL
spruceup-2024.8.20.post1.dist-info/top_level.txt
spruceup-2024.8.20.post1.dist-info/RECORD
