Metadata-Version: 2.1
Name: spruceup
Version: 2024.8.20.post1
Summary: A module for lexible identification, visualization, and removal of outliers from large multiple sequence alignments
Home-page: https://github.com/marekborowiec/spruceup
Author: Marek Borowiec
Author-email: petiolus@gmail.com
Keywords: alignment trimming outliers phylogenetics phylogenomics genomics bioinformatics
Classifier: Development Status :: 4 - Beta
Classifier: Intended Audience :: Science/Research
Classifier: Topic :: Scientific/Engineering :: Bio-Informatics
Classifier: Environment :: Console
Classifier: Programming Language :: Python :: 3
Classifier: License :: OSI Approved :: GNU General Public License v3 (GPLv3)
Classifier: Operating System :: OS Independent
Requires-Python: >=3.6.0, !=3.7.4
License-File: LICENSE
Requires-Dist: matplotlib==3.0.3
Requires-Dist: numpy==1.17
Requires-Dist: scipy==1.3.1
Requires-Dist: psutil==5.6.6
Requires-Dist: tqdm==4.29.1
Requires-Dist: treeswift==1.0.100
